tylinkmap/__init__.py
tylinkmap/cli.py
tylinkmap/linkmap.py
tylinkmap/version.py
tylinkmap-0.1.0.dist-info/DESCRIPTION.rst
tylinkmap-0.1.0.dist-info/METADATA
tylinkmap-0.1.0.dist-info/RECORD
tylinkmap-0.1.0.dist-info/WHEEL
tylinkmap-0.1.0.dist-info/entry_points.txt
tylinkmap-0.1.0.dist-info/metadata.json
tylinkmap-0.1.0.dist-info/top_level.txt
