Metadata-Version: 2.0
Name: tylinkmap
Version: 0.1.0
Summary: link map tool for iOS / macOS developers
Home-page: https://github.com/luckytianyiyan/TyLinkMap
Author: luckytianyiyan
Author-email: luckytianyiyan@gmail.com
License: MIT
Keywords: linkmap,iOS,package-size,analyze
Platform: UNKNOWN
Classifier: Development Status :: 5 - Production/Stable
Classifier: Intended Audience :: Developers
Classifier: Topic :: Software Development :: Internationalization
Classifier: Topic :: Software Development :: Interpreters
Classifier: License :: OSI Approved :: MIT License
Classifier: Programming Language :: Python :: 2.7
Requires-Dist: tabulate (>=0.7.7)
